{
    "fields": {
        "id": "UInt64",
        "push_act_flg": "Boolean",
        "push_doping_flg": "Boolean",
        "push_survey_flg": "Boolean",
        "push_admin_flg": "Boolean",
        "friend_auto_accept_flg": "Boolean",
        "result_helper_check_flg": "Boolean",
        "inherit_code": "String",
        "updated_at": "String",
        "created_at": "String"
    },
    "properties": {
        "Id": "UInt64",
        "PushActFlg": "Boolean",
        "PushHospitalRouletteFlg": "Boolean",
        "PushSurveyFlg": "Boolean",
        "PushAdminFlg": "Boolean",
        "FriendAutoAcceptFlg": "Boolean",
        "ResultHelperCheckFlg": "Boolean",
        "InheritCode": "String",
        "UpdatedAt": "String",
        "CreatedAt": "String",
        "UpdatedTime": "DateTime",
        "CreatedTime": "DateTime"
    }
}